MANIFEST.in
README.rst
setup.py
aliyunsdkims/__init__.py
aliyunsdkims/request/__init__.py
aliyunsdkims/request/v20190815/AddUserToGroupRequest.py
aliyunsdkims/request/v20190815/BindMFADeviceRequest.py
aliyunsdkims/request/v20190815/ChangePasswordRequest.py
aliyunsdkims/request/v20190815/CreateAccessKeyRequest.py
aliyunsdkims/request/v20190815/CreateGroupRequest.py
aliyunsdkims/request/v20190815/CreateLoginProfileRequest.py
aliyunsdkims/request/v20190815/CreateSAMLProviderRequest.py
aliyunsdkims/request/v20190815/CreateUserRequest.py
aliyunsdkims/request/v20190815/CreateVirtualMFADeviceRequest.py
aliyunsdkims/request/v20190815/DeleteAccessKeyRequest.py
aliyunsdkims/request/v20190815/DeleteGroupRequest.py
aliyunsdkims/request/v20190815/DeleteLoginProfileRequest.py
aliyunsdkims/request/v20190815/DeleteSAMLProviderRequest.py
aliyunsdkims/request/v20190815/DeleteUserRequest.py
aliyunsdkims/request/v20190815/DeleteVirtualMFADeviceRequest.py
aliyunsdkims/request/v20190815/DisableVirtualMFARequest.py
aliyunsdkims/request/v20190815/GetAccessKeyLastUsedRequest.py
aliyunsdkims/request/v20190815/GetAccountMFAInfoRequest.py
aliyunsdkims/request/v20190815/GetAccountSecurityPracticeReportRequest.py
aliyunsdkims/request/v20190815/GetAccountSummaryRequest.py
aliyunsdkims/request/v20190815/GetDefaultDomainRequest.py
aliyunsdkims/request/v20190815/GetGroupRequest.py
aliyunsdkims/request/v20190815/GetLoginProfileRequest.py
aliyunsdkims/request/v20190815/GetPasswordPolicyRequest.py
aliyunsdkims/request/v20190815/GetSAMLProviderRequest.py
aliyunsdkims/request/v20190815/GetSamlSsoSettingsRequest.py
aliyunsdkims/request/v20190815/GetSecurityPreferenceRequest.py
aliyunsdkims/request/v20190815/GetUserMFAInfoRequest.py
aliyunsdkims/request/v20190815/GetUserRequest.py
aliyunsdkims/request/v20190815/ListAccessKeysRequest.py
aliyunsdkims/request/v20190815/ListGroupsForUserRequest.py
aliyunsdkims/request/v20190815/ListGroupsRequest.py
aliyunsdkims/request/v20190815/ListSAMLProvidersRequest.py
dazhoubazi.egg-info/PKG-INFO
dazhoubazi.egg-info/SOURCES.txt
dazhoubazi.egg-info/dependency_links.txt
dazhoubazi.egg-info/requires.txt
dazhoubazi.egg-info/top_level.txt