Metadata-Version: 1.1
Name: dazhoubazi
Version: 1.0.0
Summary: testing.
Home-page: http://develop.aliyun.com/sdk/python
Author: tester
Author-email: livematters@live.com
License: Apache
Keywords: hyper,sdk,py
Platform: any
Classifier: Development Status :: 4 - Beta
Classifier: Intended Audience :: Developers
Classifier: License :: OSI Approved :: Apache Software License
Classifier: Programming Language :: Python
Classifier: Programming Language :: Python :: 2.6
Classifier: Programming Language :: Python :: 2.7
Classifier: Programming Language :: Python :: 3
Classifier: Programming Language :: Python :: 3.3
Classifier: Programming Language :: Python :: 3.4
Classifier: Programming Language :: Python :: 3.5
Classifier: Programming Language :: Python :: 3.6
Classifier: Topic :: Software Development
